libMcPhase-0.1.2.dist-info/RECORD
libMcPhase-0.1.2.dist-info/WHEEL
libMcPhase-0.1.2.dist-info/LICENSE
libMcPhase-0.1.2.dist-info/top_level.txt
libMcPhase-0.1.2.dist-info/METADATA
libmcphase/__init__.py
libmcphase/libmcphase.cpython-36m-x86_64-linux-gnu.so
