Metadata-Version: 2.1
Name: libMcPhase
Version: 0.1.2
Summary: A mean-field Monte Carlo simulation program for magnetic phase diagrams and excitations.
Home-page: https://github.com/mducle/libmcphase
Author: Duc Le, Martin Rotter
Author-email: duc.le@stfc.ac.uk
License: UNKNOWN
Platform: UNKNOWN
Classifier: Development Status :: 2 - Pre-Alpha
Classifier: Intended Audience :: Science/Research
Classifier: License :: OSI Approved :: GNU General Public License v3 or later (GPLv3+)
Classifier: Operating System :: Microsoft :: Windows :: Windows 10
Classifier: Operating System :: POSIX :: Linux
Classifier: Programming Language :: C++
Classifier: Programming Language :: Python :: 3
Classifier: Topic :: Scientific/Engineering :: Physics
Provides-Extra: interactive
Requires-Dist: matplotlib (>=2.2.0) ; extra == 'interactive'
